rust/lib.rs
Elo_MMR_Py-1.0.3.dist-info/METADATA
Elo_MMR_Py-1.0.3.dist-info/top_level.txt
Elo_MMR_Py-1.0.3.dist-info/WHEEL
Elo_MMR_Py-1.0.3.dist-info/RECORD
Elo_MMR_Py-1.0.3.dist-info/LICENSE
elo_mmr_py/elo_mmr_python_bindings.cpython-312-i386-linux-gnu.so
elo_mmr_py/__init__.py
Elo_MMR_Py.libs/libkeyutils-a0133cb5.so.1.5
Elo_MMR_Py.libs/libcom_err-f788d215.so.2.1
Elo_MMR_Py.libs/libgssapi_krb5-a7735118.so.2.2
Elo_MMR_Py.libs/libssl-45d6cc3d.so.1.0.2k
Elo_MMR_Py.libs/libcrypto-608e3dbc.so.1.0.2k
Elo_MMR_Py.libs/libselinux-c9aa910a.so.1
Elo_MMR_Py.libs/libkrb5-9480970b.so.3.3
Elo_MMR_Py.libs/libk5crypto-19d2ee81.so.3.1
Elo_MMR_Py.libs/libpcre-863f8bd5.so.1.2.0
Elo_MMR_Py.libs/libkrb5support-ff900cbb.so.0.1
