Metadata-Version: 2.1
Name: Elo-MMR-Py
Version: 1.0.3
Summary: Python bindings for Elo-MRR
Author: Aleksey Ropan
License: MIT License
Project-URL: Discussion, https://github.com/aropan/Elo-MMR-Py/discussions
Project-URL: Issues, https://github.com/aropan/Elo-MMR-Py/issues
Project-URL: Repository, https://github.com/aropan/Elo-MMR-Py
Keywords: rating,competition,skill,mmr,elo,trueskill,endure,glicko,python,rust
Classifier: Intended Audience :: Developers
Classifier: Intended Audience :: Science/Research
Classifier: License :: OSI Approved :: MIT License
Classifier: Operating System :: OS Independent
Classifier: Programming Language :: Python
Classifier: Programming Language :: Rust
Classifier: Topic :: Games/Entertainment
Classifier: Topic :: Software Development :: Libraries :: Python Modules
Classifier: Topic :: Utilities
License-File: LICENSE
